setup.cfg
setup.py
gbs_opt_greeks/__init__.py
gbs_opt_greeks/gbs.py
gbs_opt_greeks.egg-info/PKG-INFO
gbs_opt_greeks.egg-info/SOURCES.txt
gbs_opt_greeks.egg-info/dependency_links.txt
gbs_opt_greeks.egg-info/not-zip-safe
gbs_opt_greeks.egg-info/top_level.txt