Metadata-Version: 2.1
Name: gbs-opt-greeks
Version: 0.0
Summary: Functions for option pricing models
Home-page: UNKNOWN
Author-email: yashmahadik96@gmail.com
License: UNKNOWN
Platform: UNKNOWN
